{
 "name"         : "foxystreams",
 "repository"   : "foxystreams.repository",
 "plugin"       : "plugin.video.foxystreams",
 "priority"     : 200,
 "id"           : "foxystreams",
 "filters"      : {},
 "postprocess"  : "",
 "movies"       : [
  [
   {
    "link"      : "plugin://plugin.video.foxystreams/?mode=imdb&search={imdb}",
    "steps"     : [],
    "action"    : "PLAY"
   }
  ]
 ],
 "tvshows"      : [
  [
   {
    "link"      : "plugin://plugin.video.foxystreams/?mode=tvdb&search={id}&episode={episode}&season={season}",
    "steps"     : [],
    "action"    : "PLAY"
   }
  ]
 ]
}
